{
    "/js/app.js": "/js/app.js",
    "/css/animate.min.css": "/css/animate.min.css",
    "/css/font-awesome.min.css": "/css/font-awesome.min.css",
    "/css/bootstrap.min.css": "/css/bootstrap.min.css",
    "/css/app.css": "/css/app.css",
    "/images/404.png": "/images/404.png",
    "/images/500.png": "/images/500.png",
    "/images/avatar.jpg": "/images/avatar.jpg",
    "/images/avatar2.png": "/images/avatar2.png",
    "/images/avatar3.png": "/images/avatar3.png",
    "/images/bg.svg": "/images/bg.svg",
    "/images/bg1.jpg": "/images/bg1.jpg",
    "/images/bg2.jpg": "/images/bg2.jpg",
    "/images/bg3.jpg": "/images/bg3.jpg",
    "/images/bg4.jpg": "/images/bg4.jpg",
    "/images/bigplay.svg": "/images/bigplay.svg",
    "/images/controls.png": "/images/controls.png",
    "/images/controls.svg": "/images/controls.svg",
    "/images/demo-video.png": "/images/demo-video.png",
    "/images/g3986.png": "/images/g3986.png",
    "/images/left-bg.png": "/images/left-bg.png",
    "/images/left-bg2.png": "/images/left-bg2.png",
    "/images/logomi.png": "/images/logomi.png",
    "/images/sprite-skin-flat.png": "/images/sprite-skin-flat.png",
    "/images/sprite-skin-modern.png": "/images/sprite-skin-modern.png",
    "/images/sprite-skin-nice.png": "/images/sprite-skin-nice.png",
    "/images/sprite-skin-simple.png": "/images/sprite-skin-simple.png",
    "/images/ss.png": "/images/ss.png"
}
